MLOne/Validation.py
MLOne/__init__.py
MLOne/bias_variance.py
MLOne/classification_models.py
MLOne/driver.py
MLOne/eda.py
MLOne/interpret_results.py
MLOne/preprocessing.py
MLOne/select_variables.py
MLOne/splitter.py
MLOne-0.0.51.dist-info/LICENSE.txt
MLOne-0.0.51.dist-info/METADATA
MLOne-0.0.51.dist-info/WHEEL
MLOne-0.0.51.dist-info/top_level.txt
MLOne-0.0.51.dist-info/RECORD
