Metadata-Version: 2.1
Name: MLOne
Version: 0.0.51
Summary: A Python package with which users can just drop their dataset and download the best ML model for their dataset
Home-page: https://github.com/Dhamodaran-Babu/ML-Thunai
Author: Suhas and Dhamodaran
Author-email: srisuhas2000@gmail.com
License: UNKNOWN
Platform: UNKNOWN
Classifier: Programming Language :: Python :: 3
Classifier: License :: OSI Approved :: MIT License
Classifier: Operating System :: OS Independent
Requires-Dist: pandas
Requires-Dist: numpy
Requires-Dist: matplotlib
Requires-Dist: imblearn
Requires-Dist: sklearn
Requires-Dist: mlxtend (>=0.17.3)
Requires-Dist: seaborn
Requires-Dist: joblib
